poetry_demo_dtacs/__init__.py
poetry_demo_dtacs-0.1.7.dist-info/METADATA
poetry_demo_dtacs-0.1.7.dist-info/WHEEL
poetry_demo_dtacs-0.1.7.dist-info/RECORD
