Metadata-Version: 2.1
Name: poetry-demo-dtacs
Version: 0.1.7
Summary: Description of your package
Author: SamuelAdamsMcGuire
Author-email: s.mcguire@datatactics.de
Requires-Python: >=3.11,<4.0
Classifier: Programming Language :: Python :: 3
Classifier: Programming Language :: Python :: 3.11
Classifier: Programming Language :: Python :: 3.12
Requires-Dist: fastapi
